ytdlp_plugins/__init__.py
ytdlp_plugins/__main__.py
ytdlp_plugins/_helper.py
ytdlp_plugins/ast_utils.py
ytdlp_plugins/patching.py
ytdlp_plugins/probe.py
ytdlp_plugins/test_download.py
ytdlp_plugins/utils.py
ytdlp_plugins-2023.1.11.dist-info/LICENSE
ytdlp_plugins-2023.1.11.dist-info/METADATA
ytdlp_plugins-2023.1.11.dist-info/WHEEL
ytdlp_plugins-2023.1.11.dist-info/entry_points.txt
ytdlp_plugins-2023.1.11.dist-info/top_level.txt
ytdlp_plugins-2023.1.11.dist-info/RECORD
